{
  "toc": {
    "sections": [
      {
        "title": "command-pal",
        "source": "README.md",
        "url": "index.html",
        "slug": "index",
        "headings": [
          {
            "title": "Demos",
            "depth": 2,
            "id": "demos"
          },
          {
            "title": "Benefit's of Command Palettes",
            "depth": 2,
            "id": "benefit's-of-command-palettes"
          },
          {
            "title": "Features",
            "depth": 2,
            "id": "features"
          },
          {
            "title": "Why?",
            "depth": 2,
            "id": "why"
          },
          {
            "title": "Get Started",
            "depth": 2,
            "id": "get-started",
            "headings": [
              {
                "title": "Install",
                "depth": 3,
                "id": "install"
              },
              {
                "title": "Usage - Simple",
                "depth": 3,
                "id": "usage-simple"
              },
              {
                "title": "Usage - Advanced",
                "depth": 3,
                "id": "usage-advanced"
              }
            ]
          },
          {
            "title": "API",
            "depth": 2,
            "id": "api",
            "headings": [
              {
                "title": "CommandPal instance",
                "depth": 3,
                "id": "commandpal-instance"
              },
              {
                "title": "Subscribe to events",
                "depth": 3,
                "id": "subscribe-to-events"
              },
              {
                "title": "Command Item",
                "depth": 3,
                "id": "command-item"
              },
              {
                "title": "Command Item Child",
                "depth": 3,
                "id": "command-item-child"
              },
              {
                "title": "Add/Remove Command's At Runtime",
                "depth": 3,
                "id": "addremove-command's-at-runtime"
              },
              {
                "title": "Styling CommandPal instances",
                "depth": 3,
                "id": "styling-commandpal-instances"
              }
            ]
          },
          {
            "title": "Local Development",
            "depth": 2,
            "id": "local-development",
            "headings": [
              {
                "title": "Prevent Blur",
                "depth": 3,
                "id": "prevent-blur"
              }
            ]
          },
          {
            "title": "Prior Art",
            "depth": 2,
            "id": "prior-art"
          }
        ]
      }
    ]
  },
  "index": {
    "index.html": {
      "source": "README.md",
      "title": "command-pal",
      "pageTitle": "command-pal",
      "slug": "index",
      "headings": [
        {
          "title": "Demos",
          "depth": 2,
          "id": "demos"
        },
        {
          "title": "Benefit's of Command Palettes",
          "depth": 2,
          "id": "benefit's-of-command-palettes"
        },
        {
          "title": "Features",
          "depth": 2,
          "id": "features"
        },
        {
          "title": "Why?",
          "depth": 2,
          "id": "why"
        },
        {
          "title": "Get Started",
          "depth": 2,
          "id": "get-started",
          "headings": [
            {
              "title": "Install",
              "depth": 3,
              "id": "install"
            },
            {
              "title": "Usage - Simple",
              "depth": 3,
              "id": "usage-simple"
            },
            {
              "title": "Usage - Advanced",
              "depth": 3,
              "id": "usage-advanced"
            }
          ]
        },
        {
          "title": "API",
          "depth": 2,
          "id": "api",
          "headings": [
            {
              "title": "CommandPal instance",
              "depth": 3,
              "id": "commandpal-instance"
            },
            {
              "title": "Subscribe to events",
              "depth": 3,
              "id": "subscribe-to-events"
            },
            {
              "title": "Command Item",
              "depth": 3,
              "id": "command-item"
            },
            {
              "title": "Command Item Child",
              "depth": 3,
              "id": "command-item-child"
            },
            {
              "title": "Add/Remove Command's At Runtime",
              "depth": 3,
              "id": "addremove-command's-at-runtime"
            },
            {
              "title": "Styling CommandPal instances",
              "depth": 3,
              "id": "styling-commandpal-instances"
            }
          ]
        },
        {
          "title": "Local Development",
          "depth": 2,
          "id": "local-development",
          "headings": [
            {
              "title": "Prevent Blur",
              "depth": 3,
              "id": "prevent-blur"
            }
          ]
        },
        {
          "title": "Prior Art",
          "depth": 2,
          "id": "prior-art"
        }
      ]
    }
  },
  "sources": {
    "README.md": "index.html"
  }
}
